{
    "key": "group_62fb941608995",
    "title": "Social Media Menu",
    "fields": [
        {
            "key": "field_62fb941c17a3d",
            "label": "Social Media Icon",
            "name": "social_media_icon",
            "aria-label": "",
            "type": "select",
            "instructions": "",
            "required": 0,
            "conditional_logic": 0,
            "wrapper": {
                "width": "",
                "class": "",
                "id": ""
            },
            "choices": {
                "facebook": "Facebook",
                "twitter": "Twitter",
                "instagram": "Instagram",
                "tiktok": "TikTok",
                "linkedin": "LinkedIn",
                "medium": "Medium"
            },
            "default_value": [
                "facebook"
            ],
            "allow_null": 0,
            "multiple": 0,
            "ui": 0,
            "return_format": "value",
            "ajax": 0,
            "placeholder": ""
        }
    ],
    "location": [
        [
            {
                "param": "nav_menu_item",
                "operator": "==",
                "value": "location\/social-media"
            }
        ]
    ],
    "menu_order": 0,
    "position": "normal",
    "style": "seamless",
    "label_placement": "top",
    "instruction_placement": "label",
    "hide_on_screen": "",
    "active": true,
    "description": "",
    "show_in_rest": 0,
    "modified": 1682002493
}